modify_repos-0.2.0.dist-info/METADATA
modify_repos-0.2.0.dist-info/WHEEL
modify_repos-0.2.0.dist-info/entry_points.txt
modify_repos-0.2.0.dist-info/licenses/LICENSE.txt
modify_repos/__init__.py
modify_repos/py.typed
modify_repos/repo/__init__.py
modify_repos/repo/base.py
modify_repos/repo/git.py
modify_repos/repo/github.py
modify_repos/script/__init__.py
modify_repos/script/base.py
modify_repos/script/github.py
modify_repos/utils.py
modify_repos-0.2.0.dist-info/RECORD
