Metadata-Version: 2.4
Name: modify-repos
Version: 0.2.0
Summary: Apply changes across multiple repos at once.
Author: David Lord
License-Expression: MIT
License-File: LICENSE.txt
Requires-Python: ~=3.13.0
Requires-Dist: click>=8.1.8
Requires-Dist: jinja2>=3.1.5
Requires-Dist: platformdirs>=4.3.6
